imgcorr/__init__.py
imgcorr/corruptions.py
imgcorr/frost/frost1.png
imgcorr/frost/frost2.png
imgcorr/frost/frost3.png
imgcorr/frost/frost4.jpg
imgcorr/frost/frost5.jpg
imgcorr/frost/frost6.jpg
imgcorr-1.1.3.dist-info/LICENSE
imgcorr-1.1.3.dist-info/METADATA
imgcorr-1.1.3.dist-info/WHEEL
imgcorr-1.1.3.dist-info/top_level.txt
imgcorr-1.1.3.dist-info/RECORD
