Metadata-Version: 2.1
Name: imgcorr
Version: 1.1.3
Summary: This package provides a set of image corruptions.
Author-email: Evgenia Rusak <evgenia.rusak@bethgelab.org>, Benjamin Mitzkus <benjamin.mitzkus@bethgelab.org>, Wang Xin <xinwang614@gmail.com>
License: Apache Software License
Project-URL: Homepage, https://github.com/greatv/imgcorr
Classifier: Programming Language :: Python :: 3
Classifier: License :: OSI Approved :: Apache Software License
Classifier: Operating System :: OS Independent
Requires-Python: >=3.6
License-File: LICENSE
Requires-Dist: numpy
Requires-Dist: Pillow
Requires-Dist: scikit-image
Requires-Dist: opencv-python
Requires-Dist: scipy
Requires-Dist: numba
